duckml/__init__.py
duckml/say_quack.py
duckml-0.0.1.dist-info/METADATA
duckml-0.0.1.dist-info/WHEEL
duckml-0.0.1.dist-info/RECORD
