Metadata-Version: 2.1
Name: duckml
Version: 0.0.1
Summary: 
Author: Adithya Krishnan
Author-email: krishsandeep@gmail.com
Requires-Python: >=3.8,<4.0
Classifier: Programming Language :: Python :: 3
Classifier: Programming Language :: Python :: 3.8
Classifier: Programming Language :: Python :: 3.9
Classifier: Programming Language :: Python :: 3.10
Classifier: Programming Language :: Python :: 3.11
Classifier: Programming Language :: Python :: 3.12
Requires-Dist: duckdb (>=0.9.2,<0.10.0)
